pokemonpy/__init__.py
pokemonpy/base_pokemon.py
pokemonpy/dexpoke.py
pokemonpy/mini_moves.py
pokemonpy/moves.py
pokemonpy/older_moves.py
pokemonpy/pokemon.py
pokemonpy/texter.py
pokemonpy/trainerai.py
pokemonpy/victoryroad.py
pokemonpy/LICENSES/numpy_license.txt
pokemonpy/LICENSES/python_license.txt
pokemonpy/configurations/__init__.py
pokemonpy/configurations/config.txt
pokemonpy/configurations/default_config.txt
pokemonpy/configurations/second_config.txt
pokemonpy/documentation/CREDITS.txt
pokemonpy/documentation/game_blurb.md
pokemonpy/documentation/time_ref.txt
pokemonpy/documentation/archive/moremon.py
pokemonpy/documentation/archive/saved_dexpoke.npy
pokemonpy/documentation/archive/saved_movedex.npy
pokemonpy/documentation/archive/saved_natures.npy
pokemonpy/documentation/archive/somemons_copy.txt
pokemonpy/elite5/elite_1.npy
pokemonpy/elite5/elite_2.npy
pokemonpy/elite5/elite_3.npy
pokemonpy/elite5/elite_4.npy
pokemonpy/elite5/elite_5.npy
pokemonpy/saves/__init__.py
pokemonpy/saves/demoteam.sav
pokemonpy/saves/pypokemon.sav
pokemonpy/saves/save2.npy
pokemonpy/scripts/rungame.py
pokemonpy/somemons/__init__.py
pokemonpy/somemons/somemons.dat
pokemonpy-1.0.1.dist-info/METADATA
pokemonpy-1.0.1.dist-info/WHEEL
pokemonpy-1.0.1.dist-info/licenses/LICENSE
pokemonpy-1.0.1.dist-info/RECORD
