Metadata-Version: 2.4
Name: pokemonpy
Version: 1.0.1
Summary: This package contains a text-based game that simulates Pokémon and Pokémon battles and runs right in the terminal. Pokemon. pokemonpy. pokemon.py.
Project-URL: Homepage, https://github.com/4ntoined/pokemonpy-package
Project-URL: Issues, https://github.com/4ntoined/pokemonpy-package/issues
Author: Adarius
License-File: LICENSE
Classifier: License :: OSI Approved :: GNU General Public License v3 (GPLv3)
Classifier: Operating System :: OS Independent
Classifier: Programming Language :: Python :: 3
Requires-Python: >=3.9.0
Requires-Dist: numpy~=2.0.1
